flask_response_builder/__init__.py
flask_response_builder/builders.py
flask_response_builder/case_notation.py
flask_response_builder/config.py
flask_response_builder/dictutils.py
flask_response_builder/notations.py
flask_response_builder/response_builder.py
flask_response_builder/transformations.py
flask_response_builder/transformers.py
flask_response_builder/version.py
flask_response_builder/wrapper.py
flask_response_builder/builders/__init__.py
flask_response_builder/builders/base64.py
flask_response_builder/builders/builder.py
flask_response_builder/builders/csv.py
flask_response_builder/builders/dicttoxml.py
flask_response_builder/builders/encoders.py
flask_response_builder/builders/html.py
flask_response_builder/builders/json.py
flask_response_builder/builders/xml.py
flask_response_builder/builders/yaml.py
tests/__init__.py
tests/test_all.py
Flask_ResponseBuilder-2.0.15.dist-info/LICENSE
Flask_ResponseBuilder-2.0.15.dist-info/METADATA
Flask_ResponseBuilder-2.0.15.dist-info/WHEEL
Flask_ResponseBuilder-2.0.15.dist-info/top_level.txt
Flask_ResponseBuilder-2.0.15.dist-info/RECORD
