Metadata-Version: 2.1
Name: Flask-ResponseBuilder
Version: 2.0.15
Summary: Implementations of flask response in many format notation
Home-page: https://github.com/cs91chris/flask_response_builder
Author: cs91chris
Author-email: cs91chris@voidbrain.me
License: MIT
Platform: any
Classifier: Environment :: Web Environment
Classifier: Intended Audience :: Developers
Classifier: License :: OSI Approved :: MIT License
Classifier: Operating System :: OS Independent
Classifier: Programming Language :: Python :: 3
Classifier: Topic :: Internet :: WWW/HTTP :: Dynamic Content
Classifier: Topic :: Software Development :: Libraries :: Python Modules
Requires-Dist: Flask (>=1.0.4)
Requires-Dist: PyYAML (>=5)
Requires-Dist: xmltodict (>=0)
Requires-Dist: json2html (>=1)
